[
  {
    "gender": "GENTS",
    "scoreMin": 12,
    "scoreMax": 15,
    "products": [
      {
        "name": "Endymion",
        "image": "images/endymion.png",
        "data": "endymion"
      },
      {
        "name": "Halfeti",
        "image": "images/halfeti.png",
        "data": "halfeti"
      },
      {
        "name": "Babylon",
        "image": "images/babylon.png",
        "data": "babylon"
      }
    ]
  },
  {
    "gender": "GENTS",
    "scoreMin": 16,
    "scoreMax": 19,
    "products": [
      {
        "name": "Mr Sam",
        "image": "images/blazingmistersam.png",
        "data": "blazingmistersam"
      },
      {
        "name": "Endymion",
        "image": "images/endymion.png",
        "data": "endymion"
      },
      {
        "name": "Terryble Teddy",
        "image": "images/terribleteddy.png",
        "data": "terribleteddy"
      }
    ]
  },
  {
    "gender": "GENTS",
    "scoreMin": 20,
    "scoreMax": 23,
    "products": [
      {
        "name": "Blenheim",
        "image": "images/blenheim.png",
        "data": "blenheim"
      },
      {
        "name": "Endymion",
        "image": "images/endymion.png",
        "data": "endymion"
      },
      {
        "name": "Quercus",
        "image": "images/quercus.png",
        "data": "quercus"
      }
    ]
  },
  {
    "gender": "GENTS",
    "scoreMin": 24,
    "scoreMax": 28,
    "products": [
      {
        "name": "Sartorial",
        "image": "images/sartorial.png",
        "data": "sartorial"
      },
      {
        "name": "Endymion",
        "image": "images/endymion.png",
        "data": "endymion"
      },
      {
        "name": "Quercus",
        "image": "images/quercus.png",
        "data": "quercus"
      }
    ]
  },
  {
    "gender": "LADIES",
    "scoreMin": 12,
    "scoreMax": 15,
    "products": [
      {
        "name": "The Favourite",
        "image": "images/thefavourite.png",
        "data": "thefavourite"
      },
      {
        "name": "Constance",
        "image": "images/constance.png",
        "data": "constance"
      },
      {
        "name": "Halfeti",
        "image": "images/halfeti.png",
        "data": "halfeti"
      }
    ]
  },
  {
    "gender": "LADIES",
    "scoreMin": 16,
    "scoreMax": 19,
    "products": [
      {
        "name": "Duchess Rose",
        "image": "images/duchessrose.png",
        "data": "duchessrose"
      },
      {
        "name": "Heartless Helen",
        "image": "images/heartlesshelen.png",
        "data": "heartlesshelen"
      },
      {
        "name": "The Favourite",
        "image": "images/thefavourite.png",
        "data": "thefavourite"
      }
    ]
  },
  {
    "gender": "LADIES",
    "scoreMin": 20,
    "scoreMax": 23,
    "products": [
      {
        "name": "Duchess Rose",
        "image": "images/duchessrose.png",
        "data": "duchessrose"
      },
      {
        "name": "Luna",
        "image": "images/luna.png",
        "data": "luna"
      },
      {
        "name": "Cousin Flora",
        "image": "images/cousinflora.png",
        "data": "cousinflora"
      }
    ]
  },
  {
    "gender": "LADIES",
    "scoreMin": 24,
    "scoreMax": 28,
    "products": [
      {
        "name": "William P.",
        "image": "images/williampenhaligon.png",
        "data": "williampenhaligon"
      },
      {
        "name": "Elisabethan R",
        "image": "images/elisabethanrose.png",
        "data": "elisabethanrose"
      },
      {
        "name": "Lady Blanche",
        "image": "images/ladyblanche-bottle.png",
        "data": "ladyblanche"
      }
    ]
  },
  {
    "gender": "IT MATTERS NOT",
    "scoreMin": 12,
    "scoreMax": 15,
    "products": [
      {
        "name": "Babylon",
        "image": "images/babylon.png",
        "data": "babylon"
      },
      {
        "name": "Halfeti",
        "image": "images/halfeti.png",
        "data": "halfeti"
      },
      {
        "name": "William P",
        "image": "images/williampenhaligon.png",
        "data": "williampenhaligon"
      }
    ]
  },
  {
    "gender": "IT MATTERS NOT",
    "scoreMin": 16,
    "scoreMax": 19,
    "products": [
      {
        "name": "Quercus",
        "image": "images/quercus.png",
        "data": "quercus"
      },
      {
        "name": "Constance",
        "image": "images/constance.png",
        "data": "constance"
      },
      {
        "name": "Savoy Steam",
        "image": "images/savoysteam.png",
        "data": "savoysteam"
      }
    ]
  },
  {
    "gender": "IT MATTERS NOT",
    "scoreMin": 20,
    "scoreMax": 23,
    "products": [
      {
        "name": "Matthew",
        "image": "images/cousinmatthew.png",
        "data": "cousinmatthew"
      },
      {
        "name": "Blenheim",
        "image": "images/blenheim.png",
        "data": "blenheim"
      },
      {
        "name": "Castille",
        "image": "images/castile.png",
        "data": "castile"
      }
    ]
  },
  {
    "gender": "IT MATTERS NOT",
    "scoreMin": 24,
    "scoreMax": 28,
    "products": [
      {
        "name": "Babylon",
        "image": "images/babylon.png",
        "data": "babylon"
      },
      {
        "name": "Halfeti",
        "image": "images/halfeti.png",
        "data": "halfeti"
      },
      {
        "name": "Terryble Teddy",
        "image": "images/terribleteddy.png",
        "data": "terribleteddy"
      }
    ]
  }
]